PyPaperBot/Crossref.py
PyPaperBot/Downloader.py
PyPaperBot/HTMLparsers.py
PyPaperBot/NetInfo.py
PyPaperBot/Paper.py
PyPaperBot/PapersFilters.py
PyPaperBot/Scholar.py
PyPaperBot/Utils.py
PyPaperBot/__init__.py
PyPaperBot/__main__.py
PyPaperBot/proxy.py
PyPaperBot-1.4.1.dist-info/LICENSE.txt
PyPaperBot-1.4.1.dist-info/METADATA
PyPaperBot-1.4.1.dist-info/WHEEL
PyPaperBot-1.4.1.dist-info/entry_points.txt
PyPaperBot-1.4.1.dist-info/top_level.txt
PyPaperBot-1.4.1.dist-info/RECORD
